{
  "current_phase": 12,
  "current_step": "phase12_workflow_diagram",
  "completed_phases": [
    1,
    2,
    3,
    4,
    5,
    6,
    7,
    8,
    9,
    10,
    11
  ],
  "completed_steps": [
    "init_tracking",
    "phase1_business_understanding",
    "phase2_data_selection",
    "phase3_data_preprocessing",
    "phase4_data_transformation",
    "phase5_modeling",
    "phase6_pattern_evaluation",
    "phase7_predictor_cli",
    "phase7_controller_integration",
    "phase7_route_registration",
    "phase7_prediction_screenshots",
    "phase8_post_prediction_filtering",
    "phase9_model_versioning",
    "phase10_python_unittests",
    "phase10_php_integration_tests",
    "phase10_uat_documentation",
    "phase11_ui_toasts",
    "phase11_dashboard_logs",
    "phase11_frontend_docs",
    "phase12_workflow_diagram"
  ],
  "total_screenshots": 18,
  "start_time": "2025-10-24T15:33:16.834129Z",
  "last_update": "2025-10-26T06:18:20Z",
  "errors_encountered": 0,
  "status": "in_progress"
}
